phono/__init__.py
tests/__init__.py
tests/req_unit_test.py
tests/test_imports.py
tests/test_sanity.py
tests/data/categories.py
tests/regression/__init__.py
tests/regression/reconstruction/__init__.py
tests/regression/reconstruction/torch_audio_demo.py
Phono-0.0.1.dist-info/LICENSE.md
Phono-0.0.1.dist-info/METADATA
Phono-0.0.1.dist-info/WHEEL
Phono-0.0.1.dist-info/top_level.txt
Phono-0.0.1.dist-info/RECORD
