Metadata-Version: 2.1
Name: Phono
Version: 0.0.1
Summary: time series signal analysis
Home-page: https://github.com/aivclab/modulation
Download-URL: https://github.com/aivclab/modulation/releases
Author: Christian Heider Nielsen
Author-email: christian.heider@alexandra.dk
Maintainer: Christian Heider Nielsen
Maintainer-email: christian.heider@alexandra.dk
License: Apache License, Version 2.0
Keywords: python computer vision neo droid
Classifier: Development Status :: 4 - Beta
Classifier: Environment :: Console
Classifier: Intended Audience :: End Users/Desktop
Classifier: Intended Audience :: Developers
Classifier: License :: OSI Approved :: Apache Software License
Classifier: Operating System :: MacOS :: MacOS X
Classifier: Operating System :: Microsoft :: Windows
Classifier: Operating System :: POSIX
Classifier: Operating System :: OS Independent
Classifier: Programming Language :: Python :: 3
Classifier: Natural Language :: English
Requires-Python: >=3.6
License-File: LICENSE.md
Requires-Dist: modulation
Provides-Extra: all
Requires-Dist: pytest-cov (>=2.6.1) ; extra == 'all'
Requires-Dist: pip (>=19.0.3) ; extra == 'all'
Requires-Dist: pytest (>=4.3.0) ; extra == 'all'
Requires-Dist: pytest (>=4.4.1) ; extra == 'all'
Requires-Dist: twine (>=1.13.0) ; extra == 'all'
Requires-Dist: black[jupyter] ; extra == 'all'
Requires-Dist: pre-commit ; extra == 'all'
Requires-Dist: mock ; extra == 'all'
Requires-Dist: coveralls (>=1.6.0) ; extra == 'all'
Requires-Dist: sphinx ; extra == 'all'
Requires-Dist: wheel (>=0.33.0) ; extra == 'all'
Requires-Dist: modulation ; extra == 'all'
Provides-Extra: data
Provides-Extra: dev
Requires-Dist: pytest-cov (>=2.6.1) ; extra == 'dev'
Requires-Dist: pytest (>=4.3.0) ; extra == 'dev'
Requires-Dist: pip (>=19.0.3) ; extra == 'dev'
Requires-Dist: pytest (>=4.4.1) ; extra == 'dev'
Requires-Dist: twine (>=1.13.0) ; extra == 'dev'
Requires-Dist: black[jupyter] ; extra == 'dev'
Requires-Dist: pre-commit ; extra == 'dev'
Requires-Dist: mock ; extra == 'dev'
Requires-Dist: coveralls (>=1.6.0) ; extra == 'dev'
Requires-Dist: sphinx ; extra == 'dev'
Requires-Dist: wheel (>=0.33.0) ; extra == 'dev'
Requires-Dist: modulation ; extra == 'dev'
Provides-Extra: docs
Requires-Dist: sphinx ; extra == 'docs'
Provides-Extra: setup
Provides-Extra: tests
Requires-Dist: mock ; extra == 'tests'
Requires-Dist: pytest (>=4.4.1) ; extra == 'tests'
